mycalc/calculator.py
hyorinn-0.2.5.dist-info/METADATA
hyorinn-0.2.5.dist-info/WHEEL
hyorinn-0.2.5.dist-info/top_level.txt
hyorinn-0.2.5.dist-info/RECORD
