Metadata-Version: 2.1
Name: hyorinn
Version: 0.2.5
Summary: my calculator
Home-page: https://github.com/hyrinn/calc0725
Download-URL: https://github.com.sejin-chun/calc0001/archive/refs/tags/v0.0.1.zip
Author: cho hyo rin
License: UNKNOWN
Platform: UNKNOWN
